gatecraft/__init__.py
gatecraft/gatecraft.py
gatecraft/core/__init__.py
gatecraft/core/entity.py
gatecraft/core/policy.py
gatecraft/core/role.py
gatecraft/core/user.py
gatecraft/db/__init__.py
gatecraft/db/mock_vector_store.py
gatecraft/db/pinecone_vector_store.py
gatecraft/db/semantic_database.py
gatecraft/db/vector_store_interface.py
gatecraft/utils/__init__.py
gatecraft/utils/conditions.py
gatecraft/utils/metaclasses.py
gatecraft/utils/semantic_condition.py
gatecraft-0.1.1.dist-info/LICENSE
gatecraft-0.1.1.dist-info/METADATA
gatecraft-0.1.1.dist-info/WHEEL
gatecraft-0.1.1.dist-info/top_level.txt
gatecraft-0.1.1.dist-info/RECORD
