Metadata-Version: 2.1
Name: gatecraft
Version: 0.1.1
Summary: A semantic RBAC system with RAG capabilities
Home-page: https://github.com/lorenzoabati/gatecraft
Author: Lorenzo Abati
Author-email: lorenzo@glaidersecurity.com
Classifier: Development Status :: 3 - Alpha
Classifier: Intended Audience :: Developers
Classifier: License :: OSI Approved :: MIT License
Classifier: Operating System :: OS Independent
Classifier: Programming Language :: Python :: 3
Classifier: Programming Language :: Python :: 3.8
Classifier: Programming Language :: Python :: 3.9
Classifier: Programming Language :: Python :: 3.10
Classifier: Programming Language :: Python :: 3.11
Requires-Python: >=3.8
License-File: LICENSE
Requires-Dist: openai>=0.28.0
Requires-Dist: pinecone-client>=2.2.1
Requires-Dist: numpy>=1.21.0
Requires-Dist: python-dotenv>=0.19.0
